LICENSE-Falcon.md
MANIFEST.in
README.md
pyproject.toml
setup.py
cffi_modules/falcon-1024_clean.py
cffi_modules/falcon-512_clean.py
cffi_modules/falcon-padded-1024_clean.py
cffi_modules/falcon-padded-512_clean.py
lib/PQClean/crypto_sign/falcon-1024/clean/codec.c
lib/PQClean/crypto_sign/falcon-1024/clean/common.c
lib/PQClean/crypto_sign/falcon-1024/clean/fft.c
lib/PQClean/crypto_sign/falcon-1024/clean/fpr.c
lib/PQClean/crypto_sign/falcon-1024/clean/keygen.c
lib/PQClean/crypto_sign/falcon-1024/clean/pqclean.c
lib/PQClean/crypto_sign/falcon-1024/clean/rng.c
lib/PQClean/crypto_sign/falcon-1024/clean/sign.c
lib/PQClean/crypto_sign/falcon-1024/clean/vrfy.c
lib/PQClean/crypto_sign/falcon-1024/clean/../../../common/fips202.c
lib/PQClean/crypto_sign/falcon-1024/clean/../../../common/randombytes.c
lib/PQClean/crypto_sign/falcon-1024/clean/../../../common/sha2.c
lib/PQClean/crypto_sign/falcon-512/clean/codec.c
lib/PQClean/crypto_sign/falcon-512/clean/common.c
lib/PQClean/crypto_sign/falcon-512/clean/fft.c
lib/PQClean/crypto_sign/falcon-512/clean/fpr.c
lib/PQClean/crypto_sign/falcon-512/clean/keygen.c
lib/PQClean/crypto_sign/falcon-512/clean/pqclean.c
lib/PQClean/crypto_sign/falcon-512/clean/rng.c
lib/PQClean/crypto_sign/falcon-512/clean/sign.c
lib/PQClean/crypto_sign/falcon-512/clean/vrfy.c
lib/PQClean/crypto_sign/falcon-512/clean/../../../common/fips202.c
lib/PQClean/crypto_sign/falcon-512/clean/../../../common/randombytes.c
lib/PQClean/crypto_sign/falcon-512/clean/../../../common/sha2.c
lib/PQClean/crypto_sign/falcon-padded-1024/clean/codec.c
lib/PQClean/crypto_sign/falcon-padded-1024/clean/common.c
lib/PQClean/crypto_sign/falcon-padded-1024/clean/fft.c
lib/PQClean/crypto_sign/falcon-padded-1024/clean/fpr.c
lib/PQClean/crypto_sign/falcon-padded-1024/clean/keygen.c
lib/PQClean/crypto_sign/falcon-padded-1024/clean/pqclean.c
lib/PQClean/crypto_sign/falcon-padded-1024/clean/rng.c
lib/PQClean/crypto_sign/falcon-padded-1024/clean/sign.c
src/pypqc_cffi_bindings_falcon.egg-info/PKG-INFO
src/pypqc_cffi_bindings_falcon.egg-info/SOURCES.txt
src/pypqc_cffi_bindings_falcon.egg-info/dependency_links.txt
src/pypqc_cffi_bindings_falcon.egg-info/requires.txt
src/pypqc_cffi_bindings_falcon.egg-info/top_level.txt