Metadata-Version: 2.1
Name: pypqc-cffi-bindings-falcon
Version: 0.0.1.dev0
License: I, William Whyte, of 187 Ballardvale St. Suite A202, Wilmington MA 01803, U.S., am the owner or au-
Classifier: License :: Other/Proprietary License
Classifier: License :: OSI Approved :: MIT License
License-File: LICENSE-Falcon.md
Requires-Dist: cffi>=1.0.0; platform_python_implementation != "PyPy"
